pmarlo/__init__.py
pmarlo/_typing.py
pmarlo/_version.py
pmarlo/api.py
pmarlo/config.py
pmarlo/main.py
pmarlo/pipeline.py
pmarlo/progress.py
pmarlo/py.typed
pmarlo/results.py
pmarlo/analysis/__init__.py
pmarlo/analysis/ck.py
pmarlo/cluster/__init__.py
pmarlo/cluster/micro.py
pmarlo/cv/base.py
pmarlo/cv/deeptica.py
pmarlo/cv/pairs.py
pmarlo/data/aggregate.py
pmarlo/data/emit.py
pmarlo/data/shard.py
pmarlo/engine/__init__.py
pmarlo/engine/build.py
pmarlo/experiments/__init__.py
pmarlo/experiments/benchmark_utils.py
pmarlo/experiments/cli.py
pmarlo/experiments/kpi.py
pmarlo/experiments/msm.py
pmarlo/experiments/replica_exchange.py
pmarlo/experiments/simulation.py
pmarlo/experiments/suite.py
pmarlo/experiments/utils.py
pmarlo/features/__init__.py
pmarlo/features/base.py
pmarlo/features/builtins.py
pmarlo/fes/__init__.py
pmarlo/fes/ramachandran.py
pmarlo/fes/surfaces.py
pmarlo/io/__init__.py
pmarlo/io/trajectory.py
pmarlo/manager/__init__.py
pmarlo/manager/checkpoint_manager.py
pmarlo/markov_state_model/__init__.py
pmarlo/markov_state_model/_base.py
pmarlo/markov_state_model/_ck.py
pmarlo/markov_state_model/_clustering.py
pmarlo/markov_state_model/_estimation.py
pmarlo/markov_state_model/_export.py
pmarlo/markov_state_model/_features.py
pmarlo/markov_state_model/_fes.py
pmarlo/markov_state_model/_its.py
pmarlo/markov_state_model/_loading.py
pmarlo/markov_state_model/_plots.py
pmarlo/markov_state_model/_states.py
pmarlo/markov_state_model/_tica.py
pmarlo/markov_state_model/_tram.py
pmarlo/markov_state_model/enhanced_msm.py
pmarlo/markov_state_model/pipeline.py
pmarlo/markov_state_model/utils.py
pmarlo/protein/__init__.py
pmarlo/protein/protein.py
pmarlo/reduce/__init__.py
pmarlo/reduce/reducers.py
pmarlo/replica_exchange/__init__.py
pmarlo/replica_exchange/config.py
pmarlo/replica_exchange/demux_metadata.py
pmarlo/replica_exchange/diagnostics.py
pmarlo/replica_exchange/exchange_engine.py
pmarlo/replica_exchange/platform_selector.py
pmarlo-0.0.41.dist-info/licenses/LICENSE
pmarlo-0.0.41.dist-info/METADATA
pmarlo-0.0.41.dist-info/WHEEL
pmarlo-0.0.41.dist-info/entry_points.txt
pmarlo-0.0.41.dist-info/top_level.txt
pmarlo-0.0.41.dist-info/RECORD
