Metadata-Version: 2.4
Name: pmarlo
Version: 0.0.41
Summary: Protein Markov State Model Analysis with Replica Exchange
Author-email: PMARLO Development Team <konrad.jan.gorzelanczyk@gmail.com>
License:                     GNU GENERAL PUBLIC LICENSE
Project-URL: Homepage, https://github.com/Komputerowe-Projektowanie-Lekow/pmarlo
Project-URL: Issues, https://github.com/Komputerowe-Projektowanie-Lekow/pmarlo/issues
Keywords: molecular dynamics,markov state models,replica exchange,protein simulation,biophysics
Classifier: Development Status :: 3 - Alpha
Classifier: Intended Audience :: Science/Research
Classifier: License :: OSI Approved :: GNU General Public License v3 (GPLv3)
Classifier: Operating System :: OS Independent
Classifier: Programming Language :: Python :: 3
Classifier: Programming Language :: Python :: 3 :: Only
Classifier: Topic :: Scientific/Engineering :: Bio-Informatics
Classifier: Topic :: Scientific/Engineering :: Chemistry
Classifier: Topic :: Scientific/Engineering :: Physics
Requires-Python: <3.13,>=3.11
License-File: LICENSE
Requires-Dist: numpy<2.3,>=1.24
Requires-Dist: scipy<2.0,>=1.10
Requires-Dist: matplotlib<4.0,>=3.6
Requires-Dist: pandas<3.0,>=1.5
Requires-Dist: scikit-learn<2.0,>=1.2
Requires-Dist: mdtraj<2.0,>=1.9
Requires-Dist: openmm<9.0,>=8.0
Requires-Dist: rdkit<2025.0,>=2024.03.1
Requires-Dist: psutil<6.1,>=5.9
Requires-Dist: pygount<3.2,>=2.6
Requires-Dist: deeptime<0.5,>=0.4.5
Provides-Extra: fixer
Requires-Dist: pdbfixer>=1.9; python_version < "3.12" and extra == "fixer"
Provides-Extra: mlcv
Requires-Dist: torch>=2.2; extra == "mlcv"
Requires-Dist: mlcolvar>=1.2; extra == "mlcv"
Requires-Dist: deeptime>=0.4; extra == "mlcv"
Dynamic: license-file
